odoo8_addon_stock_available_immediately-8.0.2.0.1.99.dev21-py3.8-nspkg.pth
odoo_addons/stock_available_immediately/README.rst
odoo_addons/stock_available_immediately/__init__.py
odoo_addons/stock_available_immediately/__openerp__.py
odoo_addons/stock_available_immediately/i18n/ca.po
odoo_addons/stock_available_immediately/i18n/de.po
odoo_addons/stock_available_immediately/i18n/el_GR.po
odoo_addons/stock_available_immediately/i18n/es.po
odoo_addons/stock_available_immediately/i18n/es_ES.po
odoo_addons/stock_available_immediately/i18n/es_MX.po
odoo_addons/stock_available_immediately/i18n/fi.po
odoo_addons/stock_available_immediately/i18n/fr.po
odoo_addons/stock_available_immediately/i18n/fr_CH.po
odoo_addons/stock_available_immediately/i18n/fr_FR.po
odoo_addons/stock_available_immediately/i18n/gl.po
odoo_addons/stock_available_immediately/i18n/hr.po
odoo_addons/stock_available_immediately/i18n/hr_HR.po
odoo_addons/stock_available_immediately/i18n/it.po
odoo_addons/stock_available_immediately/i18n/nl.po
odoo_addons/stock_available_immediately/i18n/nl_NL.po
odoo_addons/stock_available_immediately/i18n/pt.po
odoo_addons/stock_available_immediately/i18n/pt_BR.po
odoo_addons/stock_available_immediately/i18n/ro.po
odoo_addons/stock_available_immediately/i18n/ru.po
odoo_addons/stock_available_immediately/i18n/sk.po
odoo_addons/stock_available_immediately/i18n/sl.po
odoo_addons/stock_available_immediately/i18n/stock_available_immediately.pot
odoo_addons/stock_available_immediately/i18n/tr.po
odoo_addons/stock_available_immediately/i18n/tr_TR.po
odoo_addons/stock_available_immediately/i18n/vi_VN.po
odoo_addons/stock_available_immediately/i18n/zh_CN.po
odoo_addons/stock_available_immediately/models/__init__.py
odoo_addons/stock_available_immediately/models/product_product.py
odoo_addons/stock_available_immediately/models/product_template.py
odoo_addons/stock_available_immediately/static/description/icon.png
odoo_addons/stock_available_immediately/tests/__init__.py
odoo8_addon_stock_available_immediately-8.0.2.0.1.99.dev21.dist-info/METADATA
odoo8_addon_stock_available_immediately-8.0.2.0.1.99.dev21.dist-info/WHEEL
odoo8_addon_stock_available_immediately-8.0.2.0.1.99.dev21.dist-info/namespace_packages.txt
odoo8_addon_stock_available_immediately-8.0.2.0.1.99.dev21.dist-info/top_level.txt
odoo8_addon_stock_available_immediately-8.0.2.0.1.99.dev21.dist-info/RECORD
