Metadata-Version: 2.1
Name: odoo8-addon-stock-available-immediately
Version: 8.0.2.0.1.99.dev21
Summary: Ignore planned receptions in quantity available to promise
Home-page: UNKNOWN
Author: Camptocamp,Odoo Community Association (OCA)
Author-email: support@odoo-community.org
License: AGPL-3
Platform: UNKNOWN
Classifier: Programming Language :: Python
Classifier: Framework :: Odoo
Classifier: Framework :: Odoo :: 8.0
Classifier: License :: OSI Approved :: GNU Affero General Public License v3
Requires-Python: ~=2.7
Requires-Dist: odoo8-addon-stock-available
Requires-Dist: odoo (<9.0a,>=8.0a)
